navigator_session/__init__.py
navigator_session/conf.py
navigator_session/data.py
navigator_session/middleware.py
navigator_session/session.py
navigator_session/version.py
navigator_session/storages/__init__.py
navigator_session/storages/abstract.py
navigator_session/storages/cookie.py
navigator_session/storages/redis.py
navigator_session-0.6.5.dist-info/LICENSE
navigator_session-0.6.5.dist-info/METADATA
navigator_session-0.6.5.dist-info/WHEEL
navigator_session-0.6.5.dist-info/top_level.txt
navigator_session-0.6.5.dist-info/RECORD
