Metadata-Version: 2.1
Name: navigator-session
Version: 0.6.5
Summary: Navigator Session allows us to store user-specific data into session object.
Home-page: https://github.com/phenobarbital/navigator-session
Author: Jesus Lara
Author-email: jesuslarag@gmail.com
License: Apache-2.0
Project-URL: Source, https://github.com/phenobarbital/navigator-session
Project-URL: Funding, https://paypal.me/phenobarbital
Project-URL: Say Thanks!, https://saythanks.io/to/phenobarbital
Keywords: asyncio,session,aioredis,aiohttp
Platform: POSIX
Classifier: Development Status :: 4 - Beta
Classifier: Intended Audience :: Developers
Classifier: Operating System :: POSIX :: Linux
Classifier: Environment :: Web Environment
Classifier: Topic :: Software Development :: Build Tools
Classifier: Topic :: Software Development :: Libraries :: Python Modules
Classifier: Topic :: Database :: Front-Ends
Classifier: Programming Language :: Python :: 3.9
Classifier: Programming Language :: Python :: 3.10
Classifier: Programming Language :: Python :: 3.11
Classifier: Programming Language :: Python :: 3.12
Classifier: Framework :: AsyncIO
Classifier: Framework :: aiohttp
Requires-Python: >=3.9.13
License-File: LICENSE
Requires-Dist: aiohttp>=3.9.5
Requires-Dist: asyncio==3.4.3
Requires-Dist: jsonpickle>=3.0.2
Requires-Dist: redis>=5.0.4
Requires-Dist: python-datamodel>=0.7.0
Requires-Dist: navconfig[default]>=1.7.0
